Metadata-Version: 2.1
Name: polinu-tools
Version: 0.1
Summary: Мои инструменты
Author-email: ruhliadapolina@gmail.com
